aiaas_falcon_light/aiaas_falcon_light.py
aiaas_falcon_light/ethic_layer/jailbreak.py
aiaas_falcon_light/ethic_layer/moderation.py
aiaas_falcon_light/logging.py
aiaas_falcon_light-0.2.5.dist-info/METADATA
aiaas_falcon_light-0.2.5.dist-info/WHEEL
aiaas_falcon_light-0.2.5.dist-info/RECORD
